paper_agent/__init__.py
paper_agent/client.py
paper_agent/main.py
paper_agent/prompt.py
paper_agent/db/__init__.py
paper_agent/db/neo.py
paper_agent/parser/__init__.py
paper_agent/parser/output_parser.py
paper_agent/tools/__init__.py
paper_agent/tools/base.py
paper_agent/tools/entity_tools.py
paper_agent/tools/graph_tools.py
paper_agent/tools/paper_tools.py
paper_agent/utils/__init__.py
paper_agent/utils/arxiv.py
paper_agent/utils/graph_utils.py
paper_agent/utils/semantic_scholar.py
paper_agent-0.0.1.dist-info/entry_points.txt
paper_agent-0.0.1.dist-info/LICENSE.txt
paper_agent-0.0.1.dist-info/WHEEL
paper_agent-0.0.1.dist-info/METADATA
paper_agent-0.0.1.dist-info/RECORD
