Metadata-Version: 2.1
Name: paper_agent
Version: 0.0.1
Summary: Agent helps you digging the paper connection!
Author-email: Zhengkai Yang <yangzhengkai.0226@bytedance.com>
Requires-Python: >=3.10
Classifier: Programming Language :: Python :: 3.10
Classifier: Operating System :: OS Independent
Requires-Dist: retry>=0.9.2
Requires-Dist: arxiv>=2.1.0
Requires-Dist: numpy>=1.26.4
Requires-Dist: scipy>=1.13.0
Requires-Dist: pandas>=2.2.2
Requires-Dist: networkx>=3.2
Requires-Dist: matplotlib>=3.8.4
Requires-Dist: neomodel>=5.3.0
Requires-Dist: langchain>=0.1.15
Requires-Dist: langchain-openai>=0.1.3
Requires-Dist: pymysql>=0.9.3
Requires-Dist: sqlalchemy>=2
Requires-Dist: fastapi==0.111.0
Requires-Dist: uvicorn==0.29.0
Requires-Dist: gunicorn==19.3.0
